{
	"data": [
		{
			"id": "1000",
			"code": "f230fh0g3",
			"name": "Aral Sea Adventure 1 stars & ends in Khiva",
			"description": "Travel Description",
			"image": "51.muynak ship cemetery.jpg",
			"price": "From $34 to $229 for one car",
			"category": "Accessories",
			"quantity": 24,
			"inventoryStatus": "INSTOCK",
			"rating": 5
		},
		{
			"id": "1001",
			"code": "nvklal433",
			"name": "Aral Sea Adventure 2 stars & ends in Khiva",
			"description": "Product Description",
			"image": "52.Mizdakhan.jpg",
			"price": 72,
			"category": "Accessories",
			"quantity": 61,
			"inventoryStatus": "INSTOCK",
			"rating": 4
		},
		{
			"id": "1002",
			"code": "zz21cz3c1",
			"name": "Aral Sea Adventure 3 stars & ends in Khiva",
			"description": "Product Description",
			"image": "53.Mizdakhan.jpg",
			"price": 79,
			"category": "Fitness",
			"quantity": 2,
			"inventoryStatus": "LOWSTOCK",
			"rating": 3
		},
		{
			"id": "1003",
			"code": "244wgerg2",
			"name": "Aral Sea Adventure 4 stars & ends in Nukus",
			"description": "Product Description",
			"image": "54.Kurgancha kala.jpg",
			"price": 29,
			"category": "Clothing",
			"quantity": 25,
			"inventoryStatus": "INSTOCK",
			"rating": 5
		},
		{
			"id": "1004",
			"code": "h456wer53",
			"name": "Aral Sea Adventure 5 stars & ends in Nukus",
			"description": "Product Description",
			"image": "55.Sudochie Lake tour.jpg",
			"price": 15,
			"category": "Accessories",
			"quantity": 73,
			"inventoryStatus": "INSTOCK",
			"rating": 4
		}
	]
}